Metadata-Version: 1.0
Name: teacher-nbextension
Version: 0.1.7
Summary: Teacher extension for Jupyter
Home-page: http://github.com/theotheo/teacher_nbextension
Author: ibelyalov
Author-email: ibelyalov@yandex.ru
License: UNKNOWN
Platform: UNKNOWN
